llm_openai.py
llm_openai_plugin-0.7.dist-info/licenses/LICENSE
llm_openai_plugin-0.7.dist-info/METADATA
llm_openai_plugin-0.7.dist-info/WHEEL
llm_openai_plugin-0.7.dist-info/entry_points.txt
llm_openai_plugin-0.7.dist-info/top_level.txt
llm_openai_plugin-0.7.dist-info/RECORD
