Metadata-Version: 2.4
Name: llm-openai-plugin
Version: 0.7
Summary: LLM plugin for OpenAI
Author: Simon Willison
License: Apache-2.0
Project-URL: Homepage, https://github.com/simonw/llm-openai-plugin
Project-URL: Changelog, https://github.com/simonw/llm-openai-plugin/releases
Project-URL: Issues, https://github.com/simonw/llm-openai-plugin/issues
Project-URL: CI, https://github.com/simonw/llm-openai-plugin/actions
Classifier: License :: OSI Approved :: Apache Software License
Requires-Python: >=3.9
License-File: LICENSE
Requires-Dist: llm>=0.23
Requires-Dist: openai>=1.67.0
Provides-Extra: test
Requires-Dist: pytest; extra == "test"
Requires-Dist: pytest-asyncio; extra == "test"
Requires-Dist: pytest-recording; extra == "test"
Requires-Dist: syrupy; extra == "test"
Requires-Dist: cogapp; extra == "test"
Dynamic: license-file
